README.md
setup.py
ubergauss/__init__.py
ubergauss/__version__.py
ubergauss/csrjax.py
ubergauss/draw.py
ubergauss/graphumap.py
ubergauss.egg-info/PKG-INFO
ubergauss.egg-info/SOURCES.txt
ubergauss.egg-info/dependency_links.txt
ubergauss.egg-info/requires.txt
ubergauss.egg-info/top_level.txt
ubergauss/optimization/__init__.py
ubergauss/optimization/bayes.py
ubergauss/optimization/blackbox.py
ubergauss/optimization/blackboxBAY.py
ubergauss/optimization/blackboxBORE.py
ubergauss/optimization/blackboxTPE.py
ubergauss/optimization/forest.py
ubergauss/tools/__init__.py
ubergauss/tools/tables.py