Metadata-Version: 2.1
Name: ubergauss
Version: 0.0.98
Summary: another machine learning library
Home-page: https://github.com/smautner/ubergauss
Author: Stefan Mautner
Author-email: myl4stn4m3stef@gmail.com
License: GPLv3
Requires-Python: >=3.8
